Metadata-Version: 2.1
Name: nextcord-ext-activities
Version: 2022.2.24.post1
Summary: An nextcord extension that helps you to launch activities on Discord.
Home-page: UNKNOWN
Author: MaskDuck
Author-email: i-am@maskduck.ninja
License: MIT
Keywords: activities
Platform: UNKNOWN
Classifier: Development Status :: 1 - Planning
Classifier: Intended Audience :: Education
Classifier: Operating System :: Microsoft :: Windows :: Windows 10
Classifier: License :: OSI Approved :: MIT License
Classifier: Programming Language :: Python :: 3
License-File: LICENSE
